supercell/__init__.py
supercell/_compat.py
supercell/acceptparsing.py
supercell/api.py
supercell/cache.py
supercell/consumer.py
supercell/decorators.py
supercell/environment.py
supercell/health.py
supercell/logging.py
supercell/mediatypes.py
supercell/middleware.py
supercell/provider.py
supercell/queryparam.py
supercell/requesthandler.py
supercell/service.py
supercell/testing.py
supercell/utils.py
supercell/version.py
supercell-0.14.0.dist-info/AUTHORS.rst
supercell-0.14.0.dist-info/LICENSE
supercell-0.14.0.dist-info/METADATA
supercell-0.14.0.dist-info/WHEEL
supercell-0.14.0.dist-info/top_level.txt
supercell-0.14.0.dist-info/RECORD
