Metadata-Version: 2.1
Name: supercell
Version: 0.14.0
Summary: Supercell is a framework for creating RESTful APIs that loosely follow the idea of domain driven design.
Home-page: http://supercell.readthedocs.org/
Author: Daniel Truemper
Author-email: truemped@gmail.com
License: http://www.apache.org/licenses/LICENSE-2.0
Platform: UNKNOWN
Classifier: Development Status :: 4 - Beta
Classifier: Intended Audience :: Developers
Classifier: License :: OSI Approved :: Apache Software License
Classifier: Programming Language :: Python :: 3.13
Classifier: Programming Language :: Python :: 3.12
Classifier: Programming Language :: Python :: 3.11
Classifier: Programming Language :: Python :: 3.10
Classifier: Programming Language :: Python :: 3.9
Classifier: Programming Language :: Python :: 3.8
Classifier: Programming Language :: Python :: 3.7
Classifier: Programming Language :: Python :: 3.6
Requires-Dist: tornado (<6.3,>=4.2.1)
Requires-Dist: schematics (>=1.1.1)
Provides-Extra: futures
Provides-Extra: test
Requires-Dist: mock ; extra == 'test'
Requires-Dist: pytest ; extra == 'test'
Requires-Dist: pytest-cov ; extra == 'test'
